{"success": true, "data": {"id": 19, "name": "deserializeme", "value": 450, "description": "[This service](https://deserializeme.chal.uiuc.tf) deserializes whatever you send it. Can you pwn it?\r\n\r\nauthor: arxenix", "category": "Web", "state": "visible", "max_attempts": 0, "type": "standard", "type_data": {"id": "standard", "name": "standard", "templates": {"create": "/plugins/challenges/assets/create.html", "update": "/plugins/challenges/assets/update.html", "view": "/plugins/challenges/assets/view.html"}, "scripts": {"create": "/plugins/challenges/assets/create.js", "update": "/plugins/challenges/assets/update.js", "view": "/plugins/challenges/assets/view.js"}}, "solves": 3, "files": ["/files/2008b19d8a6873857e4aa52a1eca3161aa1a355c7335a0c660007308/handout.tar.gz"], "tags": [], "hints": []}}
