{"success": true, "data": [{"team": 97, "challenge_id": 21, "id": 738, "user": 856, "type": "correct", "challenge": {"value": 100, "category": "Web", "name": "Just a Normal CTF"}, "date": "2020-07-18T02:55:57+00:00"}, {"team": 97, "challenge_id": 19, "id": 2635, "user": 856, "type": "correct", "challenge": {"value": 450, "category": "Web", "name": "deserializeme"}, "date": "2020-07-18T19:03:52+00:00"}, {"team": 97, "challenge_id": 48, "id": 3783, "user": 856, "type": "correct", "challenge": {"value": 50, "category": "Web", "name": "nookstop"}, "date": "2020-07-19T11:39:40+00:00"}, {"team": 97, "challenge_id": 49, "id": 3918, "user": 856, "type": "correct", "challenge": {"value": 200, "category": "Web", "name": "nookstop 2.0"}, "date": "2020-07-19T14:23:55+00:00"}]}
