{"success": true, "data": [{"team": 38, "challenge_id": 28, "id": 651, "user": 93, "type": "correct", "challenge": {"value": 20, "category": "Warmup", "name": "Spoockies"}, "date": "2020-07-18T02:30:52+00:00"}, {"team": 38, "challenge_id": 32, "id": 656, "user": 93, "type": "correct", "challenge": {"value": 20, "category": "Warmup", "name": "K.K's Mixtape"}, "date": "2020-07-18T02:32:15+00:00"}, {"team": 38, "challenge_id": 38, "id": 757, "user": 93, "type": "correct", "challenge": {"value": 100, "category": "Forensics", "name": "Raymonds Recovery"}, "date": "2020-07-18T03:02:54+00:00"}, {"team": 38, "challenge_id": 46, "id": 3538, "user": 93, "type": "correct", "challenge": {"value": 20, "category": "Misc", "name": "Feedback Survey"}, "date": "2020-07-19T06:34:20+00:00"}]}
