{"success": true, "data": [{"team": 78, "challenge_id": 38, "id": 13, "user": 215, "type": "correct", "challenge": {"value": 100, "category": "Forensics", "name": "Raymonds Recovery"}, "date": "2020-07-18T00:09:23+00:00"}, {"team": 78, "challenge_id": 32, "id": 91, "user": 215, "type": "correct", "challenge": {"value": 20, "category": "Warmup", "name": "K.K's Mixtape"}, "date": "2020-07-18T00:26:47+00:00"}, {"team": 78, "challenge_id": 29, "id": 415, "user": 215, "type": "correct", "challenge": {"value": 20, "category": "Warmup", "name": "Tom Nook Has Stonks"}, "date": "2020-07-18T01:28:15+00:00"}, {"team": 78, "challenge_id": 17, "id": 444, "user": 823, "type": "correct", "challenge": {"value": 100, "category": "Web", "name": "security_question"}, "date": "2020-07-18T01:34:41+00:00"}, {"team": 78, "challenge_id": 28, "id": 446, "user": 215, "type": "correct", "challenge": {"value": 20, "category": "Warmup", "name": "Spoockies"}, "date": "2020-07-18T01:35:29+00:00"}, {"team": 78, "challenge_id": 30, "id": 474, "user": 8, "type": "correct", "challenge": {"value": 20, "category": "Warmup", "name": "Starter OSINT"}, "date": "2020-07-18T01:39:38+00:00"}, {"team": 78, "challenge_id": 14, "id": 526, "user": 215, "type": "correct", "challenge": {"value": 40, "category": "OSINT", "name": "Isabelle's Bad Opsec 1"}, "date": "2020-07-18T01:58:26+00:00"}, {"team": 78, "challenge_id": 15, "id": 571, "user": 8, "type": "correct", "challenge": {"value": 80, "category": "OSINT", "name": "Isabelle's Bad Opsec 3"}, "date": "2020-07-18T02:09:57+00:00"}, {"team": 78, "challenge_id": 16, "id": 575, "user": 215, "type": "correct", "challenge": {"value": 40, "category": "OSINT", "name": "Isabelle's Bad Opsec 2"}, "date": "2020-07-18T02:10:30+00:00"}, {"team": 78, "challenge_id": 42, "id": 1063, "user": 8, "type": "correct", "challenge": {"value": 50, "category": "Misc", "name": "Omega Stonks"}, "date": "2020-07-18T05:16:57+00:00"}, {"team": 78, "challenge_id": 31, "id": 3061, "user": 620, "type": "correct", "challenge": {"value": 100, "category": "Crypto", "name": "Et Tu Blathers?"}, "date": "2020-07-18T23:52:58+00:00"}, {"team": 78, "challenge_id": 23, "id": 3210, "user": 823, "type": "correct", "challenge": {"value": 100, "category": "Crypto", "name": "isabelles_file_encryption"}, "date": "2020-07-19T02:33:02+00:00"}, {"team": 78, "challenge_id": 7, "id": 3229, "user": 215, "type": "correct", "challenge": {"value": 100, "category": "Kernel Exploitation", "name": "Kernel::Time_To_Start"}, "date": "2020-07-19T02:47:51+00:00"}, {"team": 78, "challenge_id": 10, "id": 3238, "user": 215, "type": "correct", "challenge": {"value": 100, "category": "Kernel Exploitation", "name": "Whats_A_Syscall?      "}, "date": "2020-07-19T02:50:59+00:00"}, {"team": 78, "challenge_id": 46, "id": 3341, "user": 8, "type": "correct", "challenge": {"value": 20, "category": "Misc", "name": "Feedback Survey"}, "date": "2020-07-19T04:03:26+00:00"}, {"team": 78, "challenge_id": 22, "id": 3391, "user": 215, "type": "correct", "challenge": {"value": 300, "category": "Crypto", "name": "coelacanth_vault"}, "date": "2020-07-19T04:43:35+00:00"}, {"team": 78, "challenge_id": 48, "id": 3916, "user": 823, "type": "correct", "challenge": {"value": 50, "category": "Web", "name": "nookstop"}, "date": "2020-07-19T14:21:51+00:00"}]}
