{"success": true, "data": {"id": 47, "name": "How to Get Started", "value": 0, "description": "Welcome to pwnyOS!\r\n\r\nTo get your credentials to access pwnyOS, please visit: https://uiuc.tf/pwnyos\r\n\r\nMore information about pwnyOS, and how to connect to a VNC server can be found here: https://github.com/sigpwny/pwnyOS-2020-docs", "category": "Kernel Exploitation", "state": "visible", "max_attempts": 0, "type": "standard", "type_data": {"id": "standard", "name": "standard", "templates": {"create": "/plugins/challenges/assets/create.html", "update": "/plugins/challenges/assets/update.html", "view": "/plugins/challenges/assets/view.html"}, "scripts": {"create": "/plugins/challenges/assets/create.js", "update": "/plugins/challenges/assets/update.js", "view": "/plugins/challenges/assets/view.js"}}, "solves": 66, "files": [], "tags": [], "hints": []}}
