{"success": true, "data": [{"team": 237, "challenge_id": 28, "id": 1620, "user": 451, "type": "correct", "challenge": {"value": 20, "category": "Warmup", "name": "Spoockies"}, "date": "2020-07-18T09:21:10+00:00"}, {"team": 237, "challenge_id": 29, "id": 1760, "user": 451, "type": "correct", "challenge": {"value": 20, "category": "Warmup", "name": "Tom Nook Has Stonks"}, "date": "2020-07-18T10:37:20+00:00"}, {"team": 237, "challenge_id": 32, "id": 1769, "user": 451, "type": "correct", "challenge": {"value": 20, "category": "Warmup", "name": "K.K's Mixtape"}, "date": "2020-07-18T10:41:16+00:00"}, {"team": 237, "challenge_id": 17, "id": 1902, "user": 451, "type": "correct", "challenge": {"value": 100, "category": "Web", "name": "security_question"}, "date": "2020-07-18T12:11:06+00:00"}, {"team": 237, "challenge_id": 46, "id": 3705, "user": 451, "type": "correct", "challenge": {"value": 20, "category": "Misc", "name": "Feedback Survey"}, "date": "2020-07-19T09:46:40+00:00"}, {"team": 237, "challenge_id": 38, "id": 3721, "user": 451, "type": "correct", "challenge": {"value": 100, "category": "Forensics", "name": "Raymonds Recovery"}, "date": "2020-07-19T10:14:49+00:00"}]}
